[
  {
    "texto": "Dado que o cliente deseja abrir uma conta, e informou o CPF, e informou o RG, e informou o endereço, quando entrar com essas informações no cadastro, então uma nova conta deve ser criada.",
    "tecnologia": "NLTK",
    "tempo": "1,37767 segundos",
    "bemFormado": true,
    "atomico": true,
    "minimo": true,
    "preCondicao": "Dado que o cliente deseja abrir uma conta , e informou o CPF , e informou o RG , e informou o endereço ,",
    "acao": "quando entrar com essas informações no cadastro ,",
    "finalidade": "então uma nova conta deve ser criada .",
    "tags": [
      "Dado --> NPROP --> SUBSTANTIVO",
      "que --> PRO-KS-REL --> PRONOME",
      "o --> ART --> ARTIGO",
      "cliente --> N --> SUBSTANTIVO",
      "deseja --> V --> VERBO",
      "abrir --> V --> VERBO",
      "uma --> ART --> ARTIGO",
      "conta --> N --> SUBSTANTIVO",
      ", --> , --> INVÁLIDO",
      "e --> KC --> CONJUNÇÃO",
      "informou --> V --> VERBO",
      "o --> ART --> ARTIGO",
      "CPF --> N --> SUBSTANTIVO",
      ", --> , --> INVÁLIDO",
      "e --> KC --> CONJUNÇÃO",
      "informou --> V --> VERBO",
      "o --> ART --> ARTIGO",
      "RG --> N --> SUBSTANTIVO",
      ", --> , --> INVÁLIDO",
      "e --> KC --> CONJUNÇÃO",
      "informou --> V --> VERBO",
      "o --> ART --> ARTIGO",
      "endereço --> N --> SUBSTANTIVO",
      ", --> , --> INVÁLIDO",
      "quando --> KS --> CONJUNÇÃO",
      "entrar --> V --> VERBO",
      "com --> PREP|+ --> INVÁLIDO",
      "essas --> PROADJ --> PRONOME",
      "informações --> N --> SUBSTANTIVO",
      "no --> PREP --> PREPOSIÇÃO",
      "cadastro --> N --> SUBSTANTIVO",
      ", --> , --> INVÁLIDO",
      "então --> ADV --> ADVÉRBIO",
      "uma --> ART --> ARTIGO",
      "nova --> ADJ --> ADJETIVO",
      "conta --> N --> SUBSTANTIVO",
      "deve --> VAUX --> VERBO AUXILIAR",
      "ser --> VAUX --> VERBO AUXILIAR",
      "criada --> PCP --> PARTICÍPIO",
      ". --> . --> INVÁLIDO"
    ],
    "erros": null
  },
  {
    "texto": "Dado que o cliente deseja abrir uma conta, e informou o CPF, e informou o RG, e informou o endereço, quando entrar com essas informações no cadastro, então uma nova conta deve ser criada.",
    "tecnologia": "spaCy",
    "tempo": "0,72515 segundos",
    "bemFormado": true,
    "atomico": true,
    "minimo": true,
    "preCondicao": "Dado que o cliente deseja abrir uma conta , e informou o CPF , e informou o RG , e informou o endereço ,",
    "acao": "quando entrar com essas informações no cadastro ,",
    "finalidade": "então uma nova conta deve ser criada .",
    "tags": [
      "Dado --> VERB --> VERBO",
      "que --> SCONJ --> CONJUNÇÃO",
      "o --> DET --> ARTIGO",
      "cliente --> NOUN --> SUBSTANTIVO",
      "deseja --> VERB --> VERBO",
      "abrir --> VERB --> VERBO",
      "uma --> DET --> ARTIGO",
      "conta --> NOUN --> SUBSTANTIVO",
      ", --> PUNCT --> INVÁLIDO",
      "e --> CCONJ --> INVÁLIDO",
      "informou --> VERB --> VERBO",
      "o --> DET --> ARTIGO",
      "CPF --> NOUN --> SUBSTANTIVO",
      ", --> PUNCT --> INVÁLIDO",
      "e --> CCONJ --> INVÁLIDO",
      "informou --> VERB --> VERBO",
      "o --> DET --> ARTIGO",
      "RG --> PROPN --> INVÁLIDO",
      ", --> PUNCT --> INVÁLIDO",
      "e --> CCONJ --> INVÁLIDO",
      "informou --> VERB --> VERBO",
      "o --> DET --> ARTIGO",
      "endereço --> NOUN --> SUBSTANTIVO",
      ", --> PUNCT --> INVÁLIDO",
      "quando --> SCONJ --> CONJUNÇÃO",
      "entrar --> VERB --> VERBO",
      "com --> ADP --> PREPOSIÇÃO",
      "essas --> DET --> ARTIGO",
      "informações --> NOUN --> SUBSTANTIVO",
      "no --> ADP --> PREPOSIÇÃO",
      "cadastro --> NOUN --> SUBSTANTIVO",
      ", --> PUNCT --> INVÁLIDO",
      "então --> ADV --> ADVÉRBIO",
      "uma --> DET --> ARTIGO",
      "nova --> ADJ --> ADJETIVO",
      "conta --> NOUN --> SUBSTANTIVO",
      "deve --> VERB --> VERBO",
      "ser --> AUX --> VERBO AUXILIAR",
      "criada --> VERB --> VERBO",
      ". --> PUNCT --> INVÁLIDO"
    ],
    "erros": null
  },
  {
    "texto": "Dado que o usuário deseja listar seus pedidos, e ele esteja logado, quando ele clicar no botão listar pedidos, então uma lista de pedidos deverá ser exibida.",
    "tecnologia": "NLTK",
    "tempo": "0,62515 segundos",
    "bemFormado": true,
    "atomico": true,
    "minimo": true,
    "preCondicao": "Dado que o usuário deseja listar seus pedidos , e ele esteja logado ,",
    "acao": "quando ele clicar no botão listar pedidos ,",
    "finalidade": "então uma lista de pedidos deverá ser exibida .",
    "tags": [
      "Dado --> NPROP --> SUBSTANTIVO",
      "que --> PRO-KS-REL --> PRONOME",
      "o --> ART --> ARTIGO",
      "usuário --> N --> SUBSTANTIVO",
      "deseja --> V --> VERBO",
      "listar --> V --> VERBO",
      "seus --> PROADJ --> PRONOME",
      "pedidos --> N --> SUBSTANTIVO",
      ", --> , --> INVÁLIDO",
      "e --> KC --> CONJUNÇÃO",
      "ele --> PROPESS --> PRONOME",
      "esteja --> VAUX --> VERBO AUXILIAR",
      "logado --> PCP --> PARTICÍPIO",
      ", --> , --> INVÁLIDO",
      "quando --> KS --> CONJUNÇÃO",
      "ele --> PROPESS --> PRONOME",
      "clicar --> V --> VERBO",
      "no --> PREP --> PREPOSIÇÃO",
      "botão --> N --> SUBSTANTIVO",
      "listar --> V --> VERBO",
      "pedidos --> N --> SUBSTANTIVO",
      ", --> , --> INVÁLIDO",
      "então --> ADV --> ADVÉRBIO",
      "uma --> ART --> ARTIGO",
      "lista --> N --> SUBSTANTIVO",
      "de --> PREP --> PREPOSIÇÃO",
      "pedidos --> N --> SUBSTANTIVO",
      "deverá --> VAUX --> VERBO AUXILIAR",
      "ser --> VAUX --> VERBO AUXILIAR",
      "exibida --> PCP --> PARTICÍPIO",
      ". --> . --> INVÁLIDO"
    ],
    "erros": null
  },
  {
    "texto": "Dado que o usuário deseja listar seus pedidos, e ele esteja logado, quando ele clicar no botão listar pedidos, então uma lista de pedidos deverá ser exibida.",
    "tecnologia": "spaCy",
    "tempo": "0,67936 segundos",
    "bemFormado": true,
    "atomico": true,
    "minimo": true,
    "preCondicao": "Dado que o usuário deseja listar seus pedidos , e ele esteja logado ,",
    "acao": "quando ele clicar no botão listar pedidos ,",
    "finalidade": "então uma lista de pedidos deverá ser exibida .",
    "tags": [
      "Dado --> VERB --> VERBO",
      "que --> SCONJ --> CONJUNÇÃO",
      "o --> DET --> ARTIGO",
      "usuário --> NOUN --> SUBSTANTIVO",
      "deseja --> VERB --> VERBO",
      "listar --> VERB --> VERBO",
      "seus --> DET --> ARTIGO",
      "pedidos --> NOUN --> SUBSTANTIVO",
      ", --> PUNCT --> INVÁLIDO",
      "e --> CCONJ --> INVÁLIDO",
      "ele --> PRON --> PRONOME",
      "esteja --> AUX --> VERBO AUXILIAR",
      "logado --> ADJ --> ADJETIVO",
      ", --> PUNCT --> INVÁLIDO",
      "quando --> SCONJ --> CONJUNÇÃO",
      "ele --> PRON --> PRONOME",
      "clicar --> VERB --> VERBO",
      "no --> ADP --> PREPOSIÇÃO",
      "botão --> NOUN --> SUBSTANTIVO",
      "listar --> VERB --> VERBO",
      "pedidos --> NOUN --> SUBSTANTIVO",
      ", --> PUNCT --> INVÁLIDO",
      "então --> ADV --> ADVÉRBIO",
      "uma --> DET --> ARTIGO",
      "lista --> NOUN --> SUBSTANTIVO",
      "de --> ADP --> PREPOSIÇÃO",
      "pedidos --> NOUN --> SUBSTANTIVO",
      "deverá --> VERB --> VERBO",
      "ser --> AUX --> VERBO AUXILIAR",
      "exibida --> VERB --> VERBO",
      ". --> PUNCT --> INVÁLIDO"
    ],
    "erros": null
  },
  {
    "texto": "Dado que o comprador deseja realizar uma compra, e adicionou os itens ao pedido, quando ele clicar no botão comprar, então um novo pedido deverá ser criado.",
    "tecnologia": "NLTK",
    "tempo": "0,62707 segundos",
    "bemFormado": true,
    "atomico": true,
    "minimo": true,
    "preCondicao": "Dado que o comprador deseja realizar uma compra , e adicionou os itens ao pedido ,",
    "acao": "quando ele clicar no botão comprar ,",
    "finalidade": "então um novo pedido deverá ser criado .",
    "tags": [
      "Dado --> NPROP --> SUBSTANTIVO",
      "que --> PRO-KS-REL --> PRONOME",
      "o --> ART --> ARTIGO",
      "comprador --> N --> SUBSTANTIVO",
      "deseja --> V --> VERBO",
      "realizar --> V --> VERBO",
      "uma --> ART --> ARTIGO",
      "compra --> N --> SUBSTANTIVO",
      ", --> , --> INVÁLIDO",
      "e --> KC --> CONJUNÇÃO",
      "adicionou --> V --> VERBO",
      "os --> ART --> ARTIGO",
      "itens --> N --> SUBSTANTIVO",
      "ao --> PREP --> PREPOSIÇÃO",
      "pedido --> N --> SUBSTANTIVO",
      ", --> , --> INVÁLIDO",
      "quando --> KS --> CONJUNÇÃO",
      "ele --> PROPESS --> PRONOME",
      "clicar --> V --> VERBO",
      "no --> PREP --> PREPOSIÇÃO",
      "botão --> N --> SUBSTANTIVO",
      "comprar --> V --> VERBO",
      ", --> , --> INVÁLIDO",
      "então --> ADV --> ADVÉRBIO",
      "um --> ART --> ARTIGO",
      "novo --> ADJ --> ADJETIVO",
      "pedido --> N --> SUBSTANTIVO",
      "deverá --> VAUX --> VERBO AUXILIAR",
      "ser --> VAUX --> VERBO AUXILIAR",
      "criado --> PCP --> PARTICÍPIO",
      ". --> . --> INVÁLIDO"
    ],
    "erros": null
  },
  {
    "texto": "Dado que o comprador deseja realizar uma compra, e adicionou os itens ao pedido, quando ele clicar no botão comprar, então um novo pedido deverá ser criado.",
    "tecnologia": "spaCy",
    "tempo": "0,69124 segundos",
    "bemFormado": true,
    "atomico": true,
    "minimo": true,
    "preCondicao": "Dado que o comprador deseja realizar uma compra , e adicionou os itens ao pedido ,",
    "acao": "quando ele clicar no botão comprar ,",
    "finalidade": "então um novo pedido deverá ser criado .",
    "tags": [
      "Dado --> VERB --> VERBO",
      "que --> SCONJ --> CONJUNÇÃO",
      "o --> DET --> ARTIGO",
      "comprador --> NOUN --> SUBSTANTIVO",
      "deseja --> VERB --> VERBO",
      "realizar --> VERB --> VERBO",
      "uma --> DET --> ARTIGO",
      "compra --> NOUN --> SUBSTANTIVO",
      ", --> PUNCT --> INVÁLIDO",
      "e --> CCONJ --> INVÁLIDO",
      "adicionou --> VERB --> VERBO",
      "os --> DET --> ARTIGO",
      "itens --> NOUN --> SUBSTANTIVO",
      "ao --> ADP --> PREPOSIÇÃO",
      "pedido --> NOUN --> SUBSTANTIVO",
      ", --> PUNCT --> INVÁLIDO",
      "quando --> SCONJ --> CONJUNÇÃO",
      "ele --> PRON --> PRONOME",
      "clicar --> VERB --> VERBO",
      "no --> ADP --> PREPOSIÇÃO",
      "botão --> NOUN --> SUBSTANTIVO",
      "comprar --> VERB --> VERBO",
      ", --> PUNCT --> INVÁLIDO",
      "então --> ADV --> ADVÉRBIO",
      "um --> DET --> ARTIGO",
      "novo --> ADJ --> ADJETIVO",
      "pedido --> NOUN --> SUBSTANTIVO",
      "deverá --> VERB --> VERBO",
      "ser --> AUX --> VERBO AUXILIAR",
      "criado --> VERB --> VERBO",
      ". --> PUNCT --> INVÁLIDO"
    ],
    "erros": null
  },
  {
    "texto": "Dado que o corretor deseja cadastrar um imóvel e que ele esteja logado, quando ele clicar no botão cadastrar e inserir os dados do imóvel então o imóvel deverá ser cadastrado.",
    "tecnologia": "NLTK",
    "tempo": "0,64662 segundos",
    "bemFormado": true,
    "atomico": true,
    "minimo": true,
    "preCondicao": "Dado que o corretor deseja cadastrar um imóvel e que ele esteja logado ,",
    "acao": "quando ele clicar no botão cadastrar e inserir os dado do imóvel",
    "finalidade": "então o imóvel deverá ser cadastrado .",
    "tags": [
      "Dado --> NPROP --> SUBSTANTIVO",
      "que --> PRO-KS-REL --> PRONOME",
      "o --> ART --> ARTIGO",
      "corretor --> N --> SUBSTANTIVO",
      "deseja --> V --> VERBO",
      "cadastrar --> V --> VERBO",
      "um --> ART --> ARTIGO",
      "imóvel --> N --> SUBSTANTIVO",
      "e --> KC --> CONJUNÇÃO",
      "que --> KS --> CONJUNÇÃO",
      "ele --> PROPESS --> PRONOME",
      "esteja --> VAUX --> VERBO AUXILIAR",
      "logado --> PCP --> PARTICÍPIO",
      ", --> , --> INVÁLIDO",
      "quando --> KS --> CONJUNÇÃO",
      "ele --> PROPESS --> PRONOME",
      "clicar --> V --> VERBO",
      "no --> PREP --> PREPOSIÇÃO",
      "botão --> N --> SUBSTANTIVO",
      "cadastrar --> V --> VERBO",
      "e --> KC --> CONJUNÇÃO",
      "inserir --> V --> VERBO",
      "os --> ART --> ARTIGO",
      "dado --> N --> SUBSTANTIVO",
      "do --> KS --> CONJUNÇÃO",
      "imóvel --> N --> SUBSTANTIVO",
      "então --> ADV --> ADVÉRBIO",
      "o --> ART --> ARTIGO",
      "imóvel --> N --> SUBSTANTIVO",
      "deverá --> VAUX --> VERBO AUXILIAR",
      "ser --> VAUX --> VERBO AUXILIAR",
      "cadastrado --> PCP --> PARTICÍPIO",
      ". --> . --> INVÁLIDO"
    ],
    "erros": null
  },
  {
    "texto": "Dado que o corretor deseja cadastrar um imóvel e que ele esteja logado, quando ele clicar no botão cadastrar e inserir os dados do imóvel então o imóvel deverá ser cadastrado.",
    "tecnologia": "spaCy",
    "tempo": "0,71142 segundos",
    "bemFormado": true,
    "atomico": true,
    "minimo": true,
    "preCondicao": "Dado que o corretor deseja cadastrar um imóvel e que ele esteja logado ,",
    "acao": "quando ele clicar no botão cadastrar e inserir os dados do imóvel",
    "finalidade": "então o imóvel deverá ser cadastrado .",
    "tags": [
      "Dado --> VERB --> VERBO",
      "que --> SCONJ --> CONJUNÇÃO",
      "o --> DET --> ARTIGO",
      "corretor --> NOUN --> SUBSTANTIVO",
      "deseja --> VERB --> VERBO",
      "cadastrar --> VERB --> VERBO",
      "um --> DET --> ARTIGO",
      "imóvel --> NOUN --> SUBSTANTIVO",
      "e --> CCONJ --> INVÁLIDO",
      "que --> PRON --> PRONOME",
      "ele --> PRON --> PRONOME",
      "esteja --> AUX --> VERBO AUXILIAR",
      "logado --> ADJ --> ADJETIVO",
      ", --> PUNCT --> INVÁLIDO",
      "quando --> SCONJ --> CONJUNÇÃO",
      "ele --> PRON --> PRONOME",
      "clicar --> VERB --> VERBO",
      "no --> ADP --> PREPOSIÇÃO",
      "botão --> NOUN --> SUBSTANTIVO",
      "cadastrar --> VERB --> VERBO",
      "e --> CCONJ --> INVÁLIDO",
      "inserir --> VERB --> VERBO",
      "os --> DET --> ARTIGO",
      "dados --> NOUN --> SUBSTANTIVO",
      "do --> ADP --> PREPOSIÇÃO",
      "imóvel --> NOUN --> SUBSTANTIVO",
      "então --> ADV --> ADVÉRBIO",
      "o --> DET --> ARTIGO",
      "imóvel --> NOUN --> SUBSTANTIVO",
      "deverá --> VERB --> VERBO",
      "ser --> AUX --> VERBO AUXILIAR",
      "cadastrado --> VERB --> VERBO",
      ". --> PUNCT --> INVÁLIDO"
    ],
    "erros": null
  },
  {
    "texto": "Dado que uma pessoa deseja se cadastrar no site, quando ela clicar no botão novo usuário, então uma nova tela será exibida para ela inserir seus dados de cadastro.",
    "tecnologia": "NLTK",
    "tempo": "0,62957 segundos",
    "bemFormado": true,
    "atomico": true,
    "minimo": true,
    "preCondicao": "Dado que uma pessoa deseja se cadastrar no site ,",
    "acao": "quando ela clicar no botão novo usuário ,",
    "finalidade": "então uma nova tela será exibida para ela inserir seus dado de cadastro .",
    "tags": [
      "Dado --> NPROP --> SUBSTANTIVO",
      "que --> PRO-KS-REL --> PRONOME",
      "uma --> ART --> ARTIGO",
      "pessoa --> N --> SUBSTANTIVO",
      "deseja --> V --> VERBO",
      "se --> PROPESS --> PRONOME",
      "cadastrar --> V --> VERBO",
      "no --> PREP --> PREPOSIÇÃO",
      "site --> N --> SUBSTANTIVO",
      ", --> , --> INVÁLIDO",
      "quando --> KS --> CONJUNÇÃO",
      "ela --> PROPESS --> PRONOME",
      "clicar --> V --> VERBO",
      "no --> PREP --> PREPOSIÇÃO",
      "botão --> N --> SUBSTANTIVO",
      "novo --> ADJ --> ADJETIVO",
      "usuário --> N --> SUBSTANTIVO",
      ", --> , --> INVÁLIDO",
      "então --> ADV --> ADVÉRBIO",
      "uma --> ART --> ARTIGO",
      "nova --> ADJ --> ADJETIVO",
      "tela --> N --> SUBSTANTIVO",
      "será --> VAUX --> VERBO AUXILIAR",
      "exibida --> PCP --> PARTICÍPIO",
      "para --> PREP --> PREPOSIÇÃO",
      "ela --> PROPESS --> PRONOME",
      "inserir --> V --> VERBO",
      "seus --> PROADJ --> PRONOME",
      "dado --> N --> SUBSTANTIVO",
      "de --> PREP --> PREPOSIÇÃO",
      "cadastro --> N --> SUBSTANTIVO",
      ". --> . --> INVÁLIDO"
    ],
    "erros": null
  },
  {
    "texto": "Dado que uma pessoa deseja se cadastrar no site, quando ela clicar no botão novo usuário, então uma nova tela será exibida para ela inserir seus dados de cadastro.",
    "tecnologia": "spaCy",
    "tempo": "0,71756 segundos",
    "bemFormado": true,
    "atomico": true,
    "minimo": true,
    "preCondicao": "Dado que uma pessoa deseja se cadastrar no site ,",
    "acao": "quando ela clicar no botão novo usuário ,",
    "finalidade": "então uma nova tela será exibida para ela inserir seus dados de cadastro .",
    "tags": [
      "Dado --> VERB --> VERBO",
      "que --> SCONJ --> CONJUNÇÃO",
      "uma --> DET --> ARTIGO",
      "pessoa --> NOUN --> SUBSTANTIVO",
      "deseja --> VERB --> VERBO",
      "se --> PRON --> PRONOME",
      "cadastrar --> VERB --> VERBO",
      "no --> ADP --> PREPOSIÇÃO",
      "site --> NOUN --> SUBSTANTIVO",
      ", --> PUNCT --> INVÁLIDO",
      "quando --> ADV --> ADVÉRBIO",
      "ela --> PRON --> PRONOME",
      "clicar --> VERB --> VERBO",
      "no --> ADP --> PREPOSIÇÃO",
      "botão --> NOUN --> SUBSTANTIVO",
      "novo --> ADJ --> ADJETIVO",
      "usuário --> NOUN --> SUBSTANTIVO",
      ", --> PUNCT --> INVÁLIDO",
      "então --> ADV --> ADVÉRBIO",
      "uma --> DET --> ARTIGO",
      "nova --> ADJ --> ADJETIVO",
      "tela --> NOUN --> SUBSTANTIVO",
      "será --> AUX --> VERBO AUXILIAR",
      "exibida --> VERB --> VERBO",
      "para --> SCONJ --> CONJUNÇÃO",
      "ela --> PRON --> PRONOME",
      "inserir --> VERB --> VERBO",
      "seus --> DET --> ARTIGO",
      "dados --> NOUN --> SUBSTANTIVO",
      "de --> ADP --> PREPOSIÇÃO",
      "cadastro --> NOUN --> SUBSTANTIVO",
      ". --> PUNCT --> INVÁLIDO"
    ],
    "erros": null
  },
  {
    "texto": "Dado que um motorista de aplicativo deseja iniciar uma corrida e ele esteja logado no sistema, quando uma nova notificação de corrida aparecer na tela e o motorista clicar em aceitar, então a localização para coleta do passageiro será exibida no GPS do aplicativo.",
    "tecnologia": "NLTK",
    "tempo": "0,66502 segundos",
    "bemFormado": true,
    "atomico": true,
    "minimo": true,
    "preCondicao": "Dado que um motorista de aplicativo deseja iniciar uma corrida e ele esteja logado no sistema ,",
    "acao": "quando uma nova notificação de corrida aparecer na tela e o motorista clicar em aceitar ,",
    "finalidade": "então a localização para coleta do passageiro será exibida no GPS do aplicativo .",
    "tags": [
      "Dado --> NPROP --> SUBSTANTIVO",
      "que --> PRO-KS-REL --> PRONOME",
      "um --> ART --> ARTIGO",
      "motorista --> N --> SUBSTANTIVO",
      "de --> PREP --> PREPOSIÇÃO",
      "aplicativo --> N --> SUBSTANTIVO",
      "deseja --> V --> VERBO",
      "iniciar --> V --> VERBO",
      "uma --> ART --> ARTIGO",
      "corrida --> N --> SUBSTANTIVO",
      "e --> KC --> CONJUNÇÃO",
      "ele --> PROPESS --> PRONOME",
      "esteja --> VAUX --> VERBO AUXILIAR",
      "logado --> PCP --> PARTICÍPIO",
      "no --> PREP --> PREPOSIÇÃO",
      "sistema --> N --> SUBSTANTIVO",
      ", --> , --> INVÁLIDO",
      "quando --> KS --> CONJUNÇÃO",
      "uma --> ART --> ARTIGO",
      "nova --> ADJ --> ADJETIVO",
      "notificação --> N --> SUBSTANTIVO",
      "de --> PREP --> PREPOSIÇÃO",
      "corrida --> N --> SUBSTANTIVO",
      "aparecer --> V --> VERBO",
      "na --> PREP --> PREPOSIÇÃO",
      "tela --> N --> SUBSTANTIVO",
      "e --> KC --> CONJUNÇÃO",
      "o --> ART --> ARTIGO",
      "motorista --> N --> SUBSTANTIVO",
      "clicar --> V --> VERBO",
      "em --> PREP --> PREPOSIÇÃO",
      "aceitar --> V --> VERBO",
      ", --> , --> INVÁLIDO",
      "então --> ADV --> ADVÉRBIO",
      "a --> ART --> ARTIGO",
      "localização --> N --> SUBSTANTIVO",
      "para --> PREP --> PREPOSIÇÃO",
      "coleta --> N --> SUBSTANTIVO",
      "do --> KS --> CONJUNÇÃO",
      "passageiro --> N --> SUBSTANTIVO",
      "será --> VAUX --> VERBO AUXILIAR",
      "exibida --> PCP --> PARTICÍPIO",
      "no --> PREP --> PREPOSIÇÃO",
      "GPS --> N --> SUBSTANTIVO",
      "do --> KS --> CONJUNÇÃO",
      "aplicativo --> N --> SUBSTANTIVO",
      ". --> . --> INVÁLIDO"
    ],
    "erros": null
  },
  {
    "texto": "Dado que um motorista de aplicativo deseja iniciar uma corrida e ele esteja logado no sistema, quando uma nova notificação de corrida aparecer na tela e o motorista clicar em aceitar, então a localização para coleta do passageiro será exibida no GPS do aplicativo.",
    "tecnologia": "spaCy",
    "tempo": "0,7477 segundos",
    "bemFormado": true,
    "atomico": true,
    "minimo": true,
    "preCondicao": "Dado que um motorista de aplicativo deseja iniciar uma corrida e ele esteja logado no sistema ,",
    "acao": "quando uma nova notificação de corrida aparecer na tela e o motorista clicar em aceitar ,",
    "finalidade": "então a localização para coleta do passageiro será exibida no GPS do aplicativo .",
    "tags": [
      "Dado --> VERB --> VERBO",
      "que --> SCONJ --> CONJUNÇÃO",
      "um --> DET --> ARTIGO",
      "motorista --> NOUN --> SUBSTANTIVO",
      "de --> ADP --> PREPOSIÇÃO",
      "aplicativo --> NOUN --> SUBSTANTIVO",
      "deseja --> VERB --> VERBO",
      "iniciar --> VERB --> VERBO",
      "uma --> DET --> ARTIGO",
      "corrida --> NOUN --> SUBSTANTIVO",
      "e --> CCONJ --> INVÁLIDO",
      "ele --> PRON --> PRONOME",
      "esteja --> AUX --> VERBO AUXILIAR",
      "logado --> VERB --> VERBO",
      "no --> ADP --> PREPOSIÇÃO",
      "sistema --> NOUN --> SUBSTANTIVO",
      ", --> PUNCT --> INVÁLIDO",
      "quando --> ADV --> ADVÉRBIO",
      "uma --> DET --> ARTIGO",
      "nova --> ADJ --> ADJETIVO",
      "notificação --> NOUN --> SUBSTANTIVO",
      "de --> ADP --> PREPOSIÇÃO",
      "corrida --> NOUN --> SUBSTANTIVO",
      "aparecer --> VERB --> VERBO",
      "na --> ADP --> PREPOSIÇÃO",
      "tela --> NOUN --> SUBSTANTIVO",
      "e --> CCONJ --> INVÁLIDO",
      "o --> DET --> ARTIGO",
      "motorista --> NOUN --> SUBSTANTIVO",
      "clicar --> VERB --> VERBO",
      "em --> SCONJ --> CONJUNÇÃO",
      "aceitar --> VERB --> VERBO",
      ", --> PUNCT --> INVÁLIDO",
      "então --> ADV --> ADVÉRBIO",
      "a --> DET --> ARTIGO",
      "localização --> NOUN --> SUBSTANTIVO",
      "para --> ADP --> PREPOSIÇÃO",
      "coleta --> NOUN --> SUBSTANTIVO",
      "do --> ADP --> PREPOSIÇÃO",
      "passageiro --> NOUN --> SUBSTANTIVO",
      "será --> AUX --> VERBO AUXILIAR",
      "exibida --> VERB --> VERBO",
      "no --> ADP --> PREPOSIÇÃO",
      "GPS --> PROPN --> INVÁLIDO",
      "do --> ADP --> PREPOSIÇÃO",
      "aplicativo --> NOUN --> SUBSTANTIVO",
      ". --> PUNCT --> INVÁLIDO"
    ],
    "erros": null
  },
  {
    "texto": "Dado que um cozinheiro deseja listar as receitas no site, quando ele clicar no botão Receitas, então uma lista de receitas em ordem alfabética deverá ser exibida.",
    "tecnologia": "NLTK",
    "tempo": "0,64939 segundos",
    "bemFormado": true,
    "atomico": true,
    "minimo": true,
    "preCondicao": "Dado que um cozinheiro deseja listar as receitas no site ,",
    "acao": "quando ele clicar no botão Receitas ,",
    "finalidade": "então uma lista de receitas em ordem alfabética deverá ser exibida .",
    "tags": [
      "Dado --> NPROP --> SUBSTANTIVO",
      "que --> PRO-KS-REL --> PRONOME",
      "um --> ART --> ARTIGO",
      "cozinheiro --> N --> SUBSTANTIVO",
      "deseja --> V --> VERBO",
      "listar --> V --> VERBO",
      "as --> ART --> ARTIGO",
      "receitas --> N --> SUBSTANTIVO",
      "no --> PREP --> PREPOSIÇÃO",
      "site --> N --> SUBSTANTIVO",
      ", --> , --> INVÁLIDO",
      "quando --> KS --> CONJUNÇÃO",
      "ele --> PROPESS --> PRONOME",
      "clicar --> V --> VERBO",
      "no --> PREP --> PREPOSIÇÃO",
      "botão --> N --> SUBSTANTIVO",
      "Receitas --> N --> SUBSTANTIVO",
      ", --> , --> INVÁLIDO",
      "então --> ADV --> ADVÉRBIO",
      "uma --> ART --> ARTIGO",
      "lista --> N --> SUBSTANTIVO",
      "de --> PREP --> PREPOSIÇÃO",
      "receitas --> N --> SUBSTANTIVO",
      "em --> PREP --> PREPOSIÇÃO",
      "ordem --> N --> SUBSTANTIVO",
      "alfabética --> ADJ --> ADJETIVO",
      "deverá --> VAUX --> VERBO AUXILIAR",
      "ser --> VAUX --> VERBO AUXILIAR",
      "exibida --> PCP --> PARTICÍPIO",
      ". --> . --> INVÁLIDO"
    ],
    "erros": null
  },
  {
    "texto": "Dado que um cozinheiro deseja listar as receitas no site, quando ele clicar no botão Receitas, então uma lista de receitas em ordem alfabética deverá ser exibida.",
    "tecnologia": "spaCy",
    "tempo": "0,7451 segundos",
    "bemFormado": true,
    "atomico": true,
    "minimo": true,
    "preCondicao": "Dado que um cozinheiro deseja listar as receitas no site ,",
    "acao": "quando ele clicar no botão Receitas ,",
    "finalidade": "então uma lista de receitas em ordem alfabética deverá ser exibida .",
    "tags": [
      "Dado --> VERB --> VERBO",
      "que --> SCONJ --> CONJUNÇÃO",
      "um --> DET --> ARTIGO",
      "cozinheiro --> NOUN --> SUBSTANTIVO",
      "deseja --> VERB --> VERBO",
      "listar --> VERB --> VERBO",
      "as --> DET --> ARTIGO",
      "receitas --> NOUN --> SUBSTANTIVO",
      "no --> ADP --> PREPOSIÇÃO",
      "site --> NOUN --> SUBSTANTIVO",
      ", --> PUNCT --> INVÁLIDO",
      "quando --> SCONJ --> CONJUNÇÃO",
      "ele --> PRON --> PRONOME",
      "clicar --> VERB --> VERBO",
      "no --> ADP --> PREPOSIÇÃO",
      "botão --> NOUN --> SUBSTANTIVO",
      "Receitas --> PROPN --> INVÁLIDO",
      ", --> PUNCT --> INVÁLIDO",
      "então --> ADV --> ADVÉRBIO",
      "uma --> DET --> ARTIGO",
      "lista --> NOUN --> SUBSTANTIVO",
      "de --> ADP --> PREPOSIÇÃO",
      "receitas --> NOUN --> SUBSTANTIVO",
      "em --> ADP --> PREPOSIÇÃO",
      "ordem --> NOUN --> SUBSTANTIVO",
      "alfabética --> ADJ --> ADJETIVO",
      "deverá --> VERB --> VERBO",
      "ser --> AUX --> VERBO AUXILIAR",
      "exibida --> VERB --> VERBO",
      ". --> PUNCT --> INVÁLIDO"
    ],
    "erros": null
  },
  {
    "texto": "Dado que um aluno deseja visualizar suas notas e ele esteja logado, quando ele clicar em seu perfil e clicar no botão Notas, então suas notas deverão ser exibidas.",
    "tecnologia": "NLTK",
    "tempo": "0,65059 segundos",
    "bemFormado": true,
    "atomico": true,
    "minimo": true,
    "preCondicao": "Dado que um aluno deseja visualizar suas notas e ele esteja logado ,",
    "acao": "quando ele clicar em seu perfil e clicar no botão Notas ,",
    "finalidade": "então suas notas deverão ser exibidas .",
    "tags": [
      "Dado --> NPROP --> SUBSTANTIVO",
      "que --> PRO-KS-REL --> PRONOME",
      "um --> ART --> ARTIGO",
      "aluno --> N --> SUBSTANTIVO",
      "deseja --> V --> VERBO",
      "visualizar --> V --> VERBO",
      "suas --> PROADJ --> PRONOME",
      "notas --> N --> SUBSTANTIVO",
      "e --> KC --> CONJUNÇÃO",
      "ele --> PROPESS --> PRONOME",
      "esteja --> VAUX --> VERBO AUXILIAR",
      "logado --> PCP --> PARTICÍPIO",
      ", --> , --> INVÁLIDO",
      "quando --> KS --> CONJUNÇÃO",
      "ele --> PROPESS --> PRONOME",
      "clicar --> V --> VERBO",
      "em --> PREP --> PREPOSIÇÃO",
      "seu --> PROADJ --> PRONOME",
      "perfil --> N --> SUBSTANTIVO",
      "e --> KC --> CONJUNÇÃO",
      "clicar --> V --> VERBO",
      "no --> PREP --> PREPOSIÇÃO",
      "botão --> N --> SUBSTANTIVO",
      "Notas --> NPROP --> SUBSTANTIVO",
      ", --> , --> INVÁLIDO",
      "então --> ADV --> ADVÉRBIO",
      "suas --> PROADJ --> PRONOME",
      "notas --> N --> SUBSTANTIVO",
      "deverão --> VAUX --> VERBO AUXILIAR",
      "ser --> VAUX --> VERBO AUXILIAR",
      "exibidas --> PCP --> PARTICÍPIO",
      ". --> . --> INVÁLIDO"
    ],
    "erros": null
  },
  {
    "texto": "Dado que um aluno deseja visualizar suas notas e ele esteja logado, quando ele clicar em seu perfil e clicar no botão Notas, então suas notas deverão ser exibidas.",
    "tecnologia": "spaCy",
    "tempo": "0,73424 segundos",
    "bemFormado": true,
    "atomico": true,
    "minimo": true,
    "preCondicao": "Dado que um aluno deseja visualizar suas notas e ele esteja logado ,",
    "acao": "quando ele clicar em seu perfil e clicar no botão Notas ,",
    "finalidade": "então suas notas deverão ser exibidas .",
    "tags": [
      "Dado --> VERB --> VERBO",
      "que --> SCONJ --> CONJUNÇÃO",
      "um --> DET --> ARTIGO",
      "aluno --> NOUN --> SUBSTANTIVO",
      "deseja --> VERB --> VERBO",
      "visualizar --> VERB --> VERBO",
      "suas --> DET --> ARTIGO",
      "notas --> NOUN --> SUBSTANTIVO",
      "e --> CCONJ --> INVÁLIDO",
      "ele --> PRON --> PRONOME",
      "esteja --> AUX --> VERBO AUXILIAR",
      "logado --> ADJ --> ADJETIVO",
      ", --> PUNCT --> INVÁLIDO",
      "quando --> SCONJ --> CONJUNÇÃO",
      "ele --> PRON --> PRONOME",
      "clicar --> VERB --> VERBO",
      "em --> ADP --> PREPOSIÇÃO",
      "seu --> DET --> ARTIGO",
      "perfil --> NOUN --> SUBSTANTIVO",
      "e --> CCONJ --> INVÁLIDO",
      "clicar --> VERB --> VERBO",
      "no --> ADP --> PREPOSIÇÃO",
      "botão --> NOUN --> SUBSTANTIVO",
      "Notas --> NOUN --> SUBSTANTIVO",
      ", --> PUNCT --> INVÁLIDO",
      "então --> ADV --> ADVÉRBIO",
      "suas --> DET --> ARTIGO",
      "notas --> NOUN --> SUBSTANTIVO",
      "deverão --> VERB --> VERBO",
      "ser --> AUX --> VERBO AUXILIAR",
      "exibidas --> VERB --> VERBO",
      ". --> PUNCT --> INVÁLIDO"
    ],
    "erros": null
  },
  {
    "texto": "Dado que o usuário deseja buscar os restaurantes mais próximos da sua localização, quando ele clicar no ícone restaurantes, então um mapa de sua localização deverá ser exibida com os restaurantes mais próximos.",
    "tecnologia": "NLTK",
    "tempo": "0,64785 segundos",
    "bemFormado": true,
    "atomico": true,
    "minimo": true,
    "preCondicao": "Dado que o usuário deseja buscar os restaurantes mais próximos da sua localização ,",
    "acao": "quando ele clicar no ícone restaurantes ,",
    "finalidade": "então um mapa de sua localização deverá ser exibida com os restaurantes mais próximos .",
    "tags": [
      "Dado --> NPROP --> SUBSTANTIVO",
      "que --> PRO-KS-REL --> PRONOME",
      "o --> ART --> ARTIGO",
      "usuário --> N --> SUBSTANTIVO",
      "deseja --> V --> VERBO",
      "buscar --> V --> VERBO",
      "os --> ART --> ARTIGO",
      "restaurantes --> N --> SUBSTANTIVO",
      "mais --> ADV --> ADVÉRBIO",
      "próximos --> ADJ --> ADJETIVO",
      "da --> NPROP --> SUBSTANTIVO",
      "sua --> NPROP --> SUBSTANTIVO",
      "localização --> N --> SUBSTANTIVO",
      ", --> , --> INVÁLIDO",
      "quando --> KS --> CONJUNÇÃO",
      "ele --> PROPESS --> PRONOME",
      "clicar --> V --> VERBO",
      "no --> PREP --> PREPOSIÇÃO",
      "ícone --> N --> SUBSTANTIVO",
      "restaurantes --> N --> SUBSTANTIVO",
      ", --> , --> INVÁLIDO",
      "então --> ADV --> ADVÉRBIO",
      "um --> ART --> ARTIGO",
      "mapa --> N --> SUBSTANTIVO",
      "de --> PREP --> PREPOSIÇÃO",
      "sua --> PROADJ --> PRONOME",
      "localização --> N --> SUBSTANTIVO",
      "deverá --> VAUX --> VERBO AUXILIAR",
      "ser --> VAUX --> VERBO AUXILIAR",
      "exibida --> PCP --> PARTICÍPIO",
      "com --> PREP --> PREPOSIÇÃO",
      "os --> ART --> ARTIGO",
      "restaurantes --> N --> SUBSTANTIVO",
      "mais --> ADV --> ADVÉRBIO",
      "próximos --> ADJ --> ADJETIVO",
      ". --> . --> INVÁLIDO"
    ],
    "erros": null
  },
  {
    "texto": "Dado que o usuário deseja buscar os restaurantes mais próximos da sua localização, quando ele clicar no ícone restaurantes, então um mapa de sua localização deverá ser exibida com os restaurantes mais próximos.",
    "tecnologia": "spaCy",
    "tempo": "0,72562 segundos",
    "bemFormado": true,
    "atomico": true,
    "minimo": true,
    "preCondicao": "Dado que o usuário deseja buscar os restaurantes mais próximos da sua localização ,",
    "acao": "quando ele clicar no ícone restaurantes ,",
    "finalidade": "então um mapa de sua localização deverá ser exibida com os restaurantes mais próximos .",
    "tags": [
      "Dado --> VERB --> VERBO",
      "que --> SCONJ --> CONJUNÇÃO",
      "o --> DET --> ARTIGO",
      "usuário --> NOUN --> SUBSTANTIVO",
      "deseja --> VERB --> VERBO",
      "buscar --> VERB --> VERBO",
      "os --> DET --> ARTIGO",
      "restaurantes --> NOUN --> SUBSTANTIVO",
      "mais --> ADV --> ADVÉRBIO",
      "próximos --> ADJ --> ADJETIVO",
      "da --> ADP --> PREPOSIÇÃO",
      "sua --> DET --> ARTIGO",
      "localização --> NOUN --> SUBSTANTIVO",
      ", --> PUNCT --> INVÁLIDO",
      "quando --> SCONJ --> CONJUNÇÃO",
      "ele --> PRON --> PRONOME",
      "clicar --> VERB --> VERBO",
      "no --> ADP --> PREPOSIÇÃO",
      "ícone --> ADJ --> ADJETIVO",
      "restaurantes --> NOUN --> SUBSTANTIVO",
      ", --> PUNCT --> INVÁLIDO",
      "então --> ADV --> ADVÉRBIO",
      "um --> DET --> ARTIGO",
      "mapa --> NOUN --> SUBSTANTIVO",
      "de --> ADP --> PREPOSIÇÃO",
      "sua --> DET --> ARTIGO",
      "localização --> NOUN --> SUBSTANTIVO",
      "deverá --> VERB --> VERBO",
      "ser --> AUX --> VERBO AUXILIAR",
      "exibida --> VERB --> VERBO",
      "com --> ADP --> PREPOSIÇÃO",
      "os --> DET --> ARTIGO",
      "restaurantes --> NOUN --> SUBSTANTIVO",
      "mais --> ADV --> ADVÉRBIO",
      "próximos --> ADJ --> ADJETIVO",
      ". --> PUNCT --> INVÁLIDO"
    ],
    "erros": null
  },
  {
    "texto": "Dado que o advogado deseja visualizar o status dos seus processos e ele esteja logado, quando ele clicar no botão Meus Processos então uma lista dos seus processos deverão ser exibidas em ordem decrescente do mais novo para o mais antigo juntamente do seu status.",
    "tecnologia": "NLTK",
    "tempo": "0,64834 segundos",
    "bemFormado": true,
    "atomico": true,
    "minimo": true,
    "preCondicao": "Dado que o advogado deseja visualizar o status do seus processos e ele esteja logado ,",
    "acao": "quando ele clicar no botão Meus Processos",
    "finalidade": "então uma lista do seus processos deverão ser exibidas em ordem decrescente do mais novo para o mais antigo juntamente do seu status .",
    "tags": [
      "Dado --> NPROP --> SUBSTANTIVO",
      "que --> PRO-KS-REL --> PRONOME",
      "o --> ART --> ARTIGO",
      "advogado --> N --> SUBSTANTIVO",
      "deseja --> V --> VERBO",
      "visualizar --> V --> VERBO",
      "o --> ART --> ARTIGO",
      "status --> N|EST --> INVÁLIDO",
      "do --> NPROP --> SUBSTANTIVO",
      "seus --> NPROP --> SUBSTANTIVO",
      "processos --> N --> SUBSTANTIVO",
      "e --> KC --> CONJUNÇÃO",
      "ele --> PROPESS --> PRONOME",
      "esteja --> VAUX --> VERBO AUXILIAR",
      "logado --> PCP --> PARTICÍPIO",
      ", --> , --> INVÁLIDO",
      "quando --> KS --> CONJUNÇÃO",
      "ele --> PROPESS --> PRONOME",
      "clicar --> V --> VERBO",
      "no --> PREP --> PREPOSIÇÃO",
      "botão --> N --> SUBSTANTIVO",
      "Meus --> PROADJ --> PRONOME",
      "Processos --> N --> SUBSTANTIVO",
      "então --> ADV --> ADVÉRBIO",
      "uma --> ART --> ARTIGO",
      "lista --> N --> SUBSTANTIVO",
      "do --> KS --> CONJUNÇÃO",
      "seus --> PROADJ --> PRONOME",
      "processos --> N --> SUBSTANTIVO",
      "deverão --> VAUX --> VERBO AUXILIAR",
      "ser --> VAUX --> VERBO AUXILIAR",
      "exibidas --> PCP --> PARTICÍPIO",
      "em --> PREP --> PREPOSIÇÃO",
      "ordem --> N --> SUBSTANTIVO",
      "decrescente --> ADJ --> ADJETIVO",
      "do --> KS --> CONJUNÇÃO",
      "mais --> ADV --> ADVÉRBIO",
      "novo --> ADV --> ADVÉRBIO",
      "para --> PREP --> PREPOSIÇÃO",
      "o --> ART --> ARTIGO",
      "mais --> ADV --> ADVÉRBIO",
      "antigo --> ADJ --> ADJETIVO",
      "juntamente --> ADV --> ADVÉRBIO",
      "do --> KS --> CONJUNÇÃO",
      "seu --> PROADJ --> PRONOME",
      "status --> N|EST --> INVÁLIDO",
      ". --> . --> INVÁLIDO"
    ],
    "erros": null
  },
  {
    "texto": "Dado que o advogado deseja visualizar o status dos seus processos e ele esteja logado, quando ele clicar no botão Meus Processos então uma lista dos seus processos deverão ser exibidas em ordem decrescente do mais novo para o mais antigo juntamente do seu status.",
    "tecnologia": "spaCy",
    "tempo": "0,73812 segundos",
    "bemFormado": true,
    "atomico": true,
    "minimo": true,
    "preCondicao": "Dado que o advogado deseja visualizar o status dos seus processos e ele esteja logado ,",
    "acao": "quando ele clicar no botão Meus Processos",
    "finalidade": "então uma lista dos seus processos deverão ser exibidas em ordem decrescente do mais novo para o mais antigo juntamente do seu status .",
    "tags": [
      "Dado --> VERB --> VERBO",
      "que --> SCONJ --> CONJUNÇÃO",
      "o --> DET --> ARTIGO",
      "advogado --> NOUN --> SUBSTANTIVO",
      "deseja --> VERB --> VERBO",
      "visualizar --> VERB --> VERBO",
      "o --> DET --> ARTIGO",
      "status --> NOUN --> SUBSTANTIVO",
      "dos --> ADP --> PREPOSIÇÃO",
      "seus --> DET --> ARTIGO",
      "processos --> NOUN --> SUBSTANTIVO",
      "e --> CCONJ --> INVÁLIDO",
      "ele --> PRON --> PRONOME",
      "esteja --> AUX --> VERBO AUXILIAR",
      "logado --> ADJ --> ADJETIVO",
      ", --> PUNCT --> INVÁLIDO",
      "quando --> SCONJ --> CONJUNÇÃO",
      "ele --> PRON --> PRONOME",
      "clicar --> VERB --> VERBO",
      "no --> ADP --> PREPOSIÇÃO",
      "botão --> NOUN --> SUBSTANTIVO",
      "Meus --> PROPN --> INVÁLIDO",
      "Processos --> PROPN --> INVÁLIDO",
      "então --> ADV --> ADVÉRBIO",
      "uma --> DET --> ARTIGO",
      "lista --> NOUN --> SUBSTANTIVO",
      "dos --> ADP --> PREPOSIÇÃO",
      "seus --> DET --> ARTIGO",
      "processos --> NOUN --> SUBSTANTIVO",
      "deverão --> VERB --> VERBO",
      "ser --> AUX --> VERBO AUXILIAR",
      "exibidas --> VERB --> VERBO",
      "em --> ADP --> PREPOSIÇÃO",
      "ordem --> NOUN --> SUBSTANTIVO",
      "decrescente --> ADJ --> ADJETIVO",
      "do --> ADP --> PREPOSIÇÃO",
      "mais --> ADV --> ADVÉRBIO",
      "novo --> ADJ --> ADJETIVO",
      "para --> ADP --> PREPOSIÇÃO",
      "o --> DET --> ARTIGO",
      "mais --> ADV --> ADVÉRBIO",
      "antigo --> ADJ --> ADJETIVO",
      "juntamente --> ADV --> ADVÉRBIO",
      "do --> ADP --> PREPOSIÇÃO",
      "seu --> DET --> ARTIGO",
      "status --> NOUN --> SUBSTANTIVO",
      ". --> PUNCT --> INVÁLIDO"
    ],
    "erros": null
  },
  {
    "texto": "Given a customer wants to open an account, and the ID was informed, and the address was informed, when all those information was typed, then a new account must be created.",
    "tecnologia": "NLTK",
    "tempo": "0,68665 segundos",
    "bemFormado": true,
    "atomico": true,
    "minimo": true,
    "preCondicao": "Given a customer want to open an account , and the ID be inform , and the address be inform ,",
    "acao": "when all those information be type ,",
    "finalidade": "then a new account must be create .",
    "tags": [
      "Given --> VBN --> VERBO",
      "a --> DT --> ARTIGO",
      "customer --> NN --> SUBSTANTIVO",
      "want --> NN --> SUBSTANTIVO",
      "to --> TO --> PREPOSIÇÃO",
      "open --> VB --> VERBO",
      "an --> DT --> ARTIGO",
      "account --> NN --> SUBSTANTIVO",
      ", --> , --> INVÁLIDO",
      "and --> CC --> CONJUNÇÃO",
      "the --> DT --> ARTIGO",
      "ID --> NNP --> SUBSTANTIVO",
      "be --> VB --> VERBO",
      "inform --> VBN --> VERBO",
      ", --> , --> INVÁLIDO",
      "and --> CC --> CONJUNÇÃO",
      "the --> DT --> ARTIGO",
      "address --> NN --> SUBSTANTIVO",
      "be --> VB --> VERBO",
      "inform --> JJ --> ADJETIVO",
      ", --> , --> INVÁLIDO",
      "when --> WRB --> ADVÉRBIO",
      "all --> DT --> ARTIGO",
      "those --> DT --> ARTIGO",
      "information --> NN --> SUBSTANTIVO",
      "be --> VB --> VERBO",
      "type --> NN --> SUBSTANTIVO",
      ", --> , --> INVÁLIDO",
      "then --> RB --> ADVÉRBIO",
      "a --> DT --> ARTIGO",
      "new --> JJ --> ADJETIVO",
      "account --> NN --> SUBSTANTIVO",
      "must --> MD --> VERBO",
      "be --> VB --> VERBO",
      "create --> NN --> SUBSTANTIVO",
      ". --> . --> INVÁLIDO"
    ],
    "erros": null
  },
  {
    "texto": "Given a customer wants to open an account, and the ID was informed, and the address was informed, when all those information was typed, then a new account must be created.",
    "tecnologia": "spaCy",
    "tempo": "1,28559 segundos",
    "bemFormado": true,
    "atomico": true,
    "minimo": true,
    "preCondicao": "Given a customer wants to open an account , and the ID was informed , and the address was informed ,",
    "acao": "when all those information was typed ,",
    "finalidade": "then a new account must be created .",
    "tags": [
      "Given --> VBN --> VERBO",
      "a --> DT --> ARTIGO",
      "customer --> NN --> SUBSTANTIVO",
      "wants --> VBZ --> VERBO",
      "to --> TO --> PREPOSIÇÃO",
      "open --> VB --> VERBO",
      "an --> DT --> ARTIGO",
      "account --> NN --> SUBSTANTIVO",
      ", --> , --> INVÁLIDO",
      "and --> CC --> CONJUNÇÃO",
      "the --> DT --> ARTIGO",
      "ID --> NNP --> SUBSTANTIVO",
      "was --> VBD --> VERBO",
      "informed --> VBN --> VERBO",
      ", --> , --> INVÁLIDO",
      "and --> CC --> CONJUNÇÃO",
      "the --> DT --> ARTIGO",
      "address --> NN --> SUBSTANTIVO",
      "was --> VBD --> VERBO",
      "informed --> VBN --> VERBO",
      ", --> , --> INVÁLIDO",
      "when --> WRB --> ADVÉRBIO",
      "all --> PDT --> INVÁLIDO",
      "those --> DT --> ARTIGO",
      "information --> NN --> SUBSTANTIVO",
      "was --> VBD --> VERBO",
      "typed --> VBN --> VERBO",
      ", --> , --> INVÁLIDO",
      "then --> RB --> ADVÉRBIO",
      "a --> DT --> ARTIGO",
      "new --> JJ --> ADJETIVO",
      "account --> NN --> SUBSTANTIVO",
      "must --> MD --> VERBO",
      "be --> VB --> VERBO",
      "created --> VBN --> VERBO",
      ". --> . --> INVÁLIDO"
    ],
    "erros": null
  },
  {
    "texto": "Given that the user wants to list his orders, and he is logged, when he clicks the list orders button, then a list of orders should be displayed.",
    "tecnologia": "NLTK",
    "tempo": "0,64321 segundos",
    "bemFormado": true,
    "atomico": true,
    "minimo": true,
    "preCondicao": "Given that the user want to list his order , and he be log ,",
    "acao": "when he click the list order button ,",
    "finalidade": "then a list of order should be display .",
    "tags": [
      "Given --> VBN --> VERBO",
      "that --> IN --> CONJUNÇÃO",
      "the --> DT --> ARTIGO",
      "user --> NN --> SUBSTANTIVO",
      "want --> VBP --> VERBO",
      "to --> TO --> PREPOSIÇÃO",
      "list --> VB --> VERBO",
      "his --> PRP$ --> PRONOME",
      "order --> NN --> SUBSTANTIVO",
      ", --> , --> INVÁLIDO",
      "and --> CC --> CONJUNÇÃO",
      "he --> PRP --> PRONOME",
      "be --> VB --> VERBO",
      "log --> VBN --> VERBO",
      ", --> , --> INVÁLIDO",
      "when --> WRB --> ADVÉRBIO",
      "he --> PRP --> PRONOME",
      "click --> VBD --> VERBO",
      "the --> DT --> ARTIGO",
      "list --> NN --> SUBSTANTIVO",
      "order --> NN --> SUBSTANTIVO",
      "button --> NN --> SUBSTANTIVO",
      ", --> , --> INVÁLIDO",
      "then --> RB --> ADVÉRBIO",
      "a --> DT --> ARTIGO",
      "list --> NN --> SUBSTANTIVO",
      "of --> IN --> CONJUNÇÃO",
      "order --> NN --> SUBSTANTIVO",
      "should --> MD --> VERBO",
      "be --> VB --> VERBO",
      "display --> NN --> SUBSTANTIVO",
      ". --> . --> INVÁLIDO"
    ],
    "erros": null
  },
  {
    "texto": "Given that the user wants to list his orders, and he is logged, when he clicks the list orders button, then a list of orders should be displayed.",
    "tecnologia": "spaCy",
    "tempo": "1,11716 segundos",
    "bemFormado": true,
    "atomico": true,
    "minimo": true,
    "preCondicao": "Given that the user wants to list his orders , and he is logged ,",
    "acao": "when he clicks the list orders button ,",
    "finalidade": "then a list of orders should be displayed .",
    "tags": [
      "Given --> VBN --> VERBO",
      "that --> IN --> CONJUNÇÃO",
      "the --> DT --> ARTIGO",
      "user --> NN --> SUBSTANTIVO",
      "wants --> VBZ --> VERBO",
      "to --> TO --> PREPOSIÇÃO",
      "list --> VB --> VERBO",
      "his --> PRP$ --> PRONOME",
      "orders --> NNS --> SUBSTANTIVO",
      ", --> , --> INVÁLIDO",
      "and --> CC --> CONJUNÇÃO",
      "he --> PRP --> PRONOME",
      "is --> VBZ --> VERBO",
      "logged --> VBN --> VERBO",
      ", --> , --> INVÁLIDO",
      "when --> WRB --> ADVÉRBIO",
      "he --> PRP --> PRONOME",
      "clicks --> VBZ --> VERBO",
      "the --> DT --> ARTIGO",
      "list --> NN --> SUBSTANTIVO",
      "orders --> NNS --> SUBSTANTIVO",
      "button --> NN --> SUBSTANTIVO",
      ", --> , --> INVÁLIDO",
      "then --> RB --> ADVÉRBIO",
      "a --> DT --> ARTIGO",
      "list --> NN --> SUBSTANTIVO",
      "of --> IN --> CONJUNÇÃO",
      "orders --> NNS --> SUBSTANTIVO",
      "should --> MD --> VERBO",
      "be --> VB --> VERBO",
      "displayed --> VBN --> VERBO",
      ". --> . --> INVÁLIDO"
    ],
    "erros": null
  },
  {
    "texto": "Given that the buyer wants to make a new order, and has added all items to the order, when he clicks on the buy button, then a new order must be created.",
    "tecnologia": "NLTK",
    "tempo": "0,67052 segundos",
    "bemFormado": true,
    "atomico": true,
    "minimo": true,
    "preCondicao": "Given that the buyer want to make a new order , and have add all items to the order ,",
    "acao": "when he click on the buy button ,",
    "finalidade": "then a new order must be create .",
    "tags": [
      "Given --> VBN --> VERBO",
      "that --> IN --> CONJUNÇÃO",
      "the --> DT --> ARTIGO",
      "buyer --> NN --> SUBSTANTIVO",
      "want --> VBP --> VERBO",
      "to --> TO --> PREPOSIÇÃO",
      "make --> VB --> VERBO",
      "a --> DT --> ARTIGO",
      "new --> JJ --> ADJETIVO",
      "order --> NN --> SUBSTANTIVO",
      ", --> , --> INVÁLIDO",
      "and --> CC --> CONJUNÇÃO",
      "have --> VBP --> VERBO",
      "add --> VBN --> VERBO",
      "all --> DT --> ARTIGO",
      "items --> NNS --> SUBSTANTIVO",
      "to --> TO --> PREPOSIÇÃO",
      "the --> DT --> ARTIGO",
      "order --> NN --> SUBSTANTIVO",
      ", --> , --> INVÁLIDO",
      "when --> WRB --> ADVÉRBIO",
      "he --> PRP --> PRONOME",
      "click --> VBZ --> VERBO",
      "on --> IN --> CONJUNÇÃO",
      "the --> DT --> ARTIGO",
      "buy --> NN --> SUBSTANTIVO",
      "button --> NN --> SUBSTANTIVO",
      ", --> , --> INVÁLIDO",
      "then --> RB --> ADVÉRBIO",
      "a --> DT --> ARTIGO",
      "new --> JJ --> ADJETIVO",
      "order --> NN --> SUBSTANTIVO",
      "must --> MD --> VERBO",
      "be --> VB --> VERBO",
      "create --> NN --> SUBSTANTIVO",
      ". --> . --> INVÁLIDO"
    ],
    "erros": null
  },
  {
    "texto": "Given that the buyer wants to make a new order, and has added all items to the order, when he clicks on the buy button, then a new order must be created.",
    "tecnologia": "spaCy",
    "tempo": "1,06305 segundos",
    "bemFormado": true,
    "atomico": true,
    "minimo": true,
    "preCondicao": "Given that the buyer wants to make a new order , and has added all items to the order ,",
    "acao": "when he clicks on the buy button ,",
    "finalidade": "then a new order must be created .",
    "tags": [
      "Given --> VBN --> VERBO",
      "that --> IN --> CONJUNÇÃO",
      "the --> DT --> ARTIGO",
      "buyer --> NN --> SUBSTANTIVO",
      "wants --> VBZ --> VERBO",
      "to --> TO --> PREPOSIÇÃO",
      "make --> VB --> VERBO",
      "a --> DT --> ARTIGO",
      "new --> JJ --> ADJETIVO",
      "order --> NN --> SUBSTANTIVO",
      ", --> , --> INVÁLIDO",
      "and --> CC --> CONJUNÇÃO",
      "has --> VBZ --> VERBO",
      "added --> VBN --> VERBO",
      "all --> DT --> ARTIGO",
      "items --> NNS --> SUBSTANTIVO",
      "to --> IN --> CONJUNÇÃO",
      "the --> DT --> ARTIGO",
      "order --> NN --> SUBSTANTIVO",
      ", --> , --> INVÁLIDO",
      "when --> WRB --> ADVÉRBIO",
      "he --> PRP --> PRONOME",
      "clicks --> VBZ --> VERBO",
      "on --> IN --> CONJUNÇÃO",
      "the --> DT --> ARTIGO",
      "buy --> NN --> SUBSTANTIVO",
      "button --> NN --> SUBSTANTIVO",
      ", --> , --> INVÁLIDO",
      "then --> RB --> ADVÉRBIO",
      "a --> DT --> ARTIGO",
      "new --> JJ --> ADJETIVO",
      "order --> NN --> SUBSTANTIVO",
      "must --> MD --> VERBO",
      "be --> VB --> VERBO",
      "created --> VBN --> VERBO",
      ". --> . --> INVÁLIDO"
    ],
    "erros": null
  },
  {
    "texto": "Given a broker wants to register a property and he is logged, when he clicks on the register button and enters the property's data, then the property must be registered.",
    "tecnologia": "NLTK",
    "tempo": "0,64231 segundos",
    "bemFormado": true,
    "atomico": true,
    "minimo": true,
    "preCondicao": "Given a broker want to register a property and he be log ,",
    "acao": "when he click on the register button and enter the property 's data ,",
    "finalidade": "then the property must be register .",
    "tags": [
      "Given --> VBN --> VERBO",
      "a --> DT --> ARTIGO",
      "broker --> NN --> SUBSTANTIVO",
      "want --> NN --> SUBSTANTIVO",
      "to --> TO --> PREPOSIÇÃO",
      "register --> VB --> VERBO",
      "a --> DT --> ARTIGO",
      "property --> NN --> SUBSTANTIVO",
      "and --> CC --> CONJUNÇÃO",
      "he --> PRP --> PRONOME",
      "be --> VB --> VERBO",
      "log --> VBN --> VERBO",
      ", --> , --> INVÁLIDO",
      "when --> WRB --> ADVÉRBIO",
      "he --> PRP --> PRONOME",
      "click --> VBZ --> VERBO",
      "on --> IN --> CONJUNÇÃO",
      "the --> DT --> ARTIGO",
      "register --> NN --> SUBSTANTIVO",
      "button --> NN --> SUBSTANTIVO",
      "and --> CC --> CONJUNÇÃO",
      "enter --> VBP --> VERBO",
      "the --> DT --> ARTIGO",
      "property --> NN --> SUBSTANTIVO",
      "'s --> POS --> INVÁLIDO",
      "data --> NNS --> SUBSTANTIVO",
      ", --> , --> INVÁLIDO",
      "then --> RB --> ADVÉRBIO",
      "the --> DT --> ARTIGO",
      "property --> NN --> SUBSTANTIVO",
      "must --> MD --> VERBO",
      "be --> VB --> VERBO",
      "register --> NN --> SUBSTANTIVO",
      ". --> . --> INVÁLIDO"
    ],
    "erros": null
  },
  {
    "texto": "Given a broker wants to register a property and he is logged, when he clicks on the register button and enters the property's data, then the property must be registered.",
    "tecnologia": "spaCy",
    "tempo": "1,26448 segundos",
    "bemFormado": true,
    "atomico": true,
    "minimo": true,
    "preCondicao": "Given a broker wants to register a property and he is logged ,",
    "acao": "when he clicks on the register button and enters the property 's data ,",
    "finalidade": "then the property must be registered .",
    "tags": [
      "Given --> VBN --> VERBO",
      "a --> DT --> ARTIGO",
      "broker --> NN --> SUBSTANTIVO",
      "wants --> VBZ --> VERBO",
      "to --> TO --> PREPOSIÇÃO",
      "register --> VB --> VERBO",
      "a --> DT --> ARTIGO",
      "property --> NN --> SUBSTANTIVO",
      "and --> CC --> CONJUNÇÃO",
      "he --> PRP --> PRONOME",
      "is --> VBZ --> VERBO",
      "logged --> VBN --> VERBO",
      ", --> , --> INVÁLIDO",
      "when --> WRB --> ADVÉRBIO",
      "he --> PRP --> PRONOME",
      "clicks --> VBZ --> VERBO",
      "on --> IN --> CONJUNÇÃO",
      "the --> DT --> ARTIGO",
      "register --> NN --> SUBSTANTIVO",
      "button --> NN --> SUBSTANTIVO",
      "and --> CC --> CONJUNÇÃO",
      "enters --> VBZ --> VERBO",
      "the --> DT --> ARTIGO",
      "property --> NN --> SUBSTANTIVO",
      "'s --> POS --> INVÁLIDO",
      "data --> NNS --> SUBSTANTIVO",
      ", --> , --> INVÁLIDO",
      "then --> RB --> ADVÉRBIO",
      "the --> DT --> ARTIGO",
      "property --> NN --> SUBSTANTIVO",
      "must --> MD --> VERBO",
      "be --> VB --> VERBO",
      "registered --> VBN --> VERBO",
      ". --> . --> INVÁLIDO"
    ],
    "erros": null
  },
  {
    "texto": "Given a person wants to register on the site, when he clicks on the New User button, then a new screen will be displayed for him to enter his data.",
    "tecnologia": "NLTK",
    "tempo": "0,66305 segundos",
    "bemFormado": true,
    "atomico": true,
    "minimo": true,
    "preCondicao": "Given a person want to register on the site ,",
    "acao": "when he click on the New User button ,",
    "finalidade": "then a new screen will be display for him to enter his data .",
    "tags": [
      "Given --> VBN --> VERBO",
      "a --> DT --> ARTIGO",
      "person --> NN --> SUBSTANTIVO",
      "want --> VBP --> VERBO",
      "to --> TO --> PREPOSIÇÃO",
      "register --> VB --> VERBO",
      "on --> IN --> CONJUNÇÃO",
      "the --> DT --> ARTIGO",
      "site --> NN --> SUBSTANTIVO",
      ", --> , --> INVÁLIDO",
      "when --> WRB --> ADVÉRBIO",
      "he --> PRP --> PRONOME",
      "click --> VBZ --> VERBO",
      "on --> IN --> CONJUNÇÃO",
      "the --> DT --> ARTIGO",
      "New --> NNP --> SUBSTANTIVO",
      "User --> NNP --> SUBSTANTIVO",
      "button --> NN --> SUBSTANTIVO",
      ", --> , --> INVÁLIDO",
      "then --> RB --> ADVÉRBIO",
      "a --> DT --> ARTIGO",
      "new --> JJ --> ADJETIVO",
      "screen --> NN --> SUBSTANTIVO",
      "will --> MD --> VERBO",
      "be --> VB --> VERBO",
      "display --> VBN --> VERBO",
      "for --> IN --> CONJUNÇÃO",
      "him --> PRP --> PRONOME",
      "to --> TO --> PREPOSIÇÃO",
      "enter --> VB --> VERBO",
      "his --> PRP$ --> PRONOME",
      "data --> NNS --> SUBSTANTIVO",
      ". --> . --> INVÁLIDO"
    ],
    "erros": null
  },
  {
    "texto": "Given a person wants to register on the site, when he clicks on the New User button, then a new screen will be displayed for him to enter his data.",
    "tecnologia": "spaCy",
    "tempo": "1,07353 segundos",
    "bemFormado": true,
    "atomico": true,
    "minimo": true,
    "preCondicao": "Given a person wants to register on the site ,",
    "acao": "when he clicks on the New User button ,",
    "finalidade": "then a new screen will be displayed for him to enter his data .",
    "tags": [
      "Given --> VBN --> VERBO",
      "a --> DT --> ARTIGO",
      "person --> NN --> SUBSTANTIVO",
      "wants --> VBZ --> VERBO",
      "to --> TO --> PREPOSIÇÃO",
      "register --> VB --> VERBO",
      "on --> IN --> CONJUNÇÃO",
      "the --> DT --> ARTIGO",
      "site --> NN --> SUBSTANTIVO",
      ", --> , --> INVÁLIDO",
      "when --> WRB --> ADVÉRBIO",
      "he --> PRP --> PRONOME",
      "clicks --> VBZ --> VERBO",
      "on --> IN --> CONJUNÇÃO",
      "the --> DT --> ARTIGO",
      "New --> NNP --> SUBSTANTIVO",
      "User --> NNP --> SUBSTANTIVO",
      "button --> NN --> SUBSTANTIVO",
      ", --> , --> INVÁLIDO",
      "then --> RB --> ADVÉRBIO",
      "a --> DT --> ARTIGO",
      "new --> JJ --> ADJETIVO",
      "screen --> NN --> SUBSTANTIVO",
      "will --> MD --> VERBO",
      "be --> VB --> VERBO",
      "displayed --> VBN --> VERBO",
      "for --> IN --> CONJUNÇÃO",
      "him --> PRP --> PRONOME",
      "to --> TO --> PREPOSIÇÃO",
      "enter --> VB --> VERBO",
      "his --> PRP$ --> PRONOME",
      "data --> NNS --> SUBSTANTIVO",
      ". --> . --> INVÁLIDO"
    ],
    "erros": null
  },
  {
    "texto": "Given that an app driver wants to start a ride and he is logged, when a new ride notification appears on the screen and the driver clicks on accept, then the pick-up location of the passenger will be displayed on the GPS of the app.",
    "tecnologia": "NLTK",
    "tempo": "0,63552 segundos",
    "bemFormado": true,
    "atomico": true,
    "minimo": true,
    "preCondicao": "Given that an app driver want to start a ride and he be log ,",
    "acao": "when a new ride notification appear on the screen and the driver click on accept ,",
    "finalidade": "then the pick-up location of the passenger will be display on the GPS of the app .",
    "tags": [
      "Given --> VBN --> VERBO",
      "that --> IN --> CONJUNÇÃO",
      "an --> DT --> ARTIGO",
      "app --> JJ --> ADJETIVO",
      "driver --> NN --> SUBSTANTIVO",
      "want --> VBP --> VERBO",
      "to --> TO --> PREPOSIÇÃO",
      "start --> VB --> VERBO",
      "a --> DT --> ARTIGO",
      "ride --> NN --> SUBSTANTIVO",
      "and --> CC --> CONJUNÇÃO",
      "he --> PRP --> PRONOME",
      "be --> VB --> VERBO",
      "log --> VBN --> VERBO",
      ", --> , --> INVÁLIDO",
      "when --> WRB --> ADVÉRBIO",
      "a --> DT --> ARTIGO",
      "new --> JJ --> ADJETIVO",
      "ride --> NN --> SUBSTANTIVO",
      "notification --> NN --> SUBSTANTIVO",
      "appear --> VBP --> VERBO",
      "on --> IN --> CONJUNÇÃO",
      "the --> DT --> ARTIGO",
      "screen --> NN --> SUBSTANTIVO",
      "and --> CC --> CONJUNÇÃO",
      "the --> DT --> ARTIGO",
      "driver --> NN --> SUBSTANTIVO",
      "click --> NN --> SUBSTANTIVO",
      "on --> IN --> CONJUNÇÃO",
      "accept --> NN --> SUBSTANTIVO",
      ", --> , --> INVÁLIDO",
      "then --> RB --> ADVÉRBIO",
      "the --> DT --> ARTIGO",
      "pick-up --> JJ --> ADJETIVO",
      "location --> NN --> SUBSTANTIVO",
      "of --> IN --> CONJUNÇÃO",
      "the --> DT --> ARTIGO",
      "passenger --> NN --> SUBSTANTIVO",
      "will --> MD --> VERBO",
      "be --> VB --> VERBO",
      "display --> VBN --> VERBO",
      "on --> IN --> CONJUNÇÃO",
      "the --> DT --> ARTIGO",
      "GPS --> NNP --> SUBSTANTIVO",
      "of --> IN --> CONJUNÇÃO",
      "the --> DT --> ARTIGO",
      "app --> NN --> SUBSTANTIVO",
      ". --> . --> INVÁLIDO"
    ],
    "erros": null
  },
  {
    "texto": "Given that an app driver wants to start a ride and he is logged, when a new ride notification appears on the screen and the driver clicks on accept, then the pick-up location of the passenger will be displayed on the GPS of the app.",
    "tecnologia": "spaCy",
    "tempo": "1,05063 segundos",
    "bemFormado": true,
    "atomico": true,
    "minimo": true,
    "preCondicao": "Given that an app driver wants to start a ride and he is logged ,",
    "acao": "when a new ride notification appears on the screen and the driver clicks on accept ,",
    "finalidade": "then the pick - up location of the passenger will be displayed on the GPS of the app .",
    "tags": [
      "Given --> VBN --> VERBO",
      "that --> IN --> CONJUNÇÃO",
      "an --> DT --> ARTIGO",
      "app --> NN --> SUBSTANTIVO",
      "driver --> NN --> SUBSTANTIVO",
      "wants --> VBZ --> VERBO",
      "to --> TO --> PREPOSIÇÃO",
      "start --> VB --> VERBO",
      "a --> DT --> ARTIGO",
      "ride --> NN --> SUBSTANTIVO",
      "and --> CC --> CONJUNÇÃO",
      "he --> PRP --> PRONOME",
      "is --> VBZ --> VERBO",
      "logged --> VBN --> VERBO",
      ", --> , --> INVÁLIDO",
      "when --> WRB --> ADVÉRBIO",
      "a --> DT --> ARTIGO",
      "new --> JJ --> ADJETIVO",
      "ride --> NN --> SUBSTANTIVO",
      "notification --> NN --> SUBSTANTIVO",
      "appears --> VBZ --> VERBO",
      "on --> IN --> CONJUNÇÃO",
      "the --> DT --> ARTIGO",
      "screen --> NN --> SUBSTANTIVO",
      "and --> CC --> CONJUNÇÃO",
      "the --> DT --> ARTIGO",
      "driver --> NN --> SUBSTANTIVO",
      "clicks --> VBZ --> VERBO",
      "on --> RP --> PARTICÍPIO",
      "accept --> VB --> VERBO",
      ", --> , --> INVÁLIDO",
      "then --> RB --> ADVÉRBIO",
      "the --> DT --> ARTIGO",
      "pick --> VB --> VERBO",
      "- --> HYPH --> INVÁLIDO",
      "up --> RP --> PARTICÍPIO",
      "location --> NN --> SUBSTANTIVO",
      "of --> IN --> CONJUNÇÃO",
      "the --> DT --> ARTIGO",
      "passenger --> NN --> SUBSTANTIVO",
      "will --> MD --> VERBO",
      "be --> VB --> VERBO",
      "displayed --> VBN --> VERBO",
      "on --> IN --> CONJUNÇÃO",
      "the --> DT --> ARTIGO",
      "GPS --> NNP --> SUBSTANTIVO",
      "of --> IN --> CONJUNÇÃO",
      "the --> DT --> ARTIGO",
      "app --> NN --> SUBSTANTIVO",
      ". --> . --> INVÁLIDO"
    ],
    "erros": null
  },
  {
    "texto": "Given a cook wants to list the recipes on the website, when he clicks on the Recipes button, then a list of recipes in alphabetical order should be displayed.",
    "tecnologia": "NLTK",
    "tempo": "0,64387 segundos",
    "bemFormado": true,
    "atomico": true,
    "minimo": true,
    "preCondicao": "Given a cook want to list the recipes on the website ,",
    "acao": "when he click on the Recipes button ,",
    "finalidade": "then a list of recipes in alphabetical order should be display .",
    "tags": [
      "Given --> VBN --> VERBO",
      "a --> DT --> ARTIGO",
      "cook --> NN --> SUBSTANTIVO",
      "want --> NN --> SUBSTANTIVO",
      "to --> TO --> PREPOSIÇÃO",
      "list --> VB --> VERBO",
      "the --> DT --> ARTIGO",
      "recipes --> NNS --> SUBSTANTIVO",
      "on --> IN --> CONJUNÇÃO",
      "the --> DT --> ARTIGO",
      "website --> NN --> SUBSTANTIVO",
      ", --> , --> INVÁLIDO",
      "when --> WRB --> ADVÉRBIO",
      "he --> PRP --> PRONOME",
      "click --> VBZ --> VERBO",
      "on --> IN --> CONJUNÇÃO",
      "the --> DT --> ARTIGO",
      "Recipes --> NNP --> SUBSTANTIVO",
      "button --> NN --> SUBSTANTIVO",
      ", --> , --> INVÁLIDO",
      "then --> RB --> ADVÉRBIO",
      "a --> DT --> ARTIGO",
      "list --> NN --> SUBSTANTIVO",
      "of --> IN --> CONJUNÇÃO",
      "recipes --> NNS --> SUBSTANTIVO",
      "in --> IN --> CONJUNÇÃO",
      "alphabetical --> JJ --> ADJETIVO",
      "order --> NN --> SUBSTANTIVO",
      "should --> MD --> VERBO",
      "be --> VB --> VERBO",
      "display --> NN --> SUBSTANTIVO",
      ". --> . --> INVÁLIDO"
    ],
    "erros": null
  },
  {
    "texto": "Given a cook wants to list the recipes on the website, when he clicks on the Recipes button, then a list of recipes in alphabetical order should be displayed.",
    "tecnologia": "spaCy",
    "tempo": "1,18987 segundos",
    "bemFormado": true,
    "atomico": true,
    "minimo": true,
    "preCondicao": "Given a cook wants to list the recipes on the website ,",
    "acao": "when he clicks on the Recipes button ,",
    "finalidade": "then a list of recipes in alphabetical order should be displayed .",
    "tags": [
      "Given --> VBN --> VERBO",
      "a --> DT --> ARTIGO",
      "cook --> NN --> SUBSTANTIVO",
      "wants --> VBZ --> VERBO",
      "to --> TO --> PREPOSIÇÃO",
      "list --> VB --> VERBO",
      "the --> DT --> ARTIGO",
      "recipes --> NNS --> SUBSTANTIVO",
      "on --> IN --> CONJUNÇÃO",
      "the --> DT --> ARTIGO",
      "website --> NN --> SUBSTANTIVO",
      ", --> , --> INVÁLIDO",
      "when --> WRB --> ADVÉRBIO",
      "he --> PRP --> PRONOME",
      "clicks --> VBZ --> VERBO",
      "on --> IN --> CONJUNÇÃO",
      "the --> DT --> ARTIGO",
      "Recipes --> NNPS --> INVÁLIDO",
      "button --> NN --> SUBSTANTIVO",
      ", --> , --> INVÁLIDO",
      "then --> RB --> ADVÉRBIO",
      "a --> DT --> ARTIGO",
      "list --> NN --> SUBSTANTIVO",
      "of --> IN --> CONJUNÇÃO",
      "recipes --> NNS --> SUBSTANTIVO",
      "in --> IN --> CONJUNÇÃO",
      "alphabetical --> JJ --> ADJETIVO",
      "order --> NN --> SUBSTANTIVO",
      "should --> MD --> VERBO",
      "be --> VB --> VERBO",
      "displayed --> VBN --> VERBO",
      ". --> . --> INVÁLIDO"
    ],
    "erros": null
  },
  {
    "texto": "Given that a student wants to check his grades and he is logged, when he clicks on his profile and clicks the Grades button, then his grades should be displayed.",
    "tecnologia": "NLTK",
    "tempo": "0,64181 segundos",
    "bemFormado": true,
    "atomico": true,
    "minimo": true,
    "preCondicao": "Given that a student want to check his grade and he be log ,",
    "acao": "when he click on his profile and click the Grades button ,",
    "finalidade": "then his grade should be display .",
    "tags": [
      "Given --> VBN --> VERBO",
      "that --> IN --> CONJUNÇÃO",
      "a --> DT --> ARTIGO",
      "student --> NN --> SUBSTANTIVO",
      "want --> NN --> SUBSTANTIVO",
      "to --> TO --> PREPOSIÇÃO",
      "check --> VB --> VERBO",
      "his --> PRP$ --> PRONOME",
      "grade --> NN --> SUBSTANTIVO",
      "and --> CC --> CONJUNÇÃO",
      "he --> PRP --> PRONOME",
      "be --> VB --> VERBO",
      "log --> VBN --> VERBO",
      ", --> , --> INVÁLIDO",
      "when --> WRB --> ADVÉRBIO",
      "he --> PRP --> PRONOME",
      "click --> VB --> VERBO",
      "on --> IN --> CONJUNÇÃO",
      "his --> PRP$ --> PRONOME",
      "profile --> NN --> SUBSTANTIVO",
      "and --> CC --> CONJUNÇÃO",
      "click --> VB --> VERBO",
      "the --> DT --> ARTIGO",
      "Grades --> NNP --> SUBSTANTIVO",
      "button --> NN --> SUBSTANTIVO",
      ", --> , --> INVÁLIDO",
      "then --> RB --> ADVÉRBIO",
      "his --> PRP$ --> PRONOME",
      "grade --> NN --> SUBSTANTIVO",
      "should --> MD --> VERBO",
      "be --> VB --> VERBO",
      "display --> NN --> SUBSTANTIVO",
      ". --> . --> INVÁLIDO"
    ],
    "erros": null
  },
  {
    "texto": "Given that a student wants to check his grades and he is logged, when he clicks on his profile and clicks the Grades button, then his grades should be displayed.",
    "tecnologia": "spaCy",
    "tempo": "1,04397 segundos",
    "bemFormado": true,
    "atomico": true,
    "minimo": true,
    "preCondicao": "Given that a student wants to check his grades and he is logged ,",
    "acao": "when he clicks on his profile and clicks the Grades button ,",
    "finalidade": "then his grades should be displayed .",
    "tags": [
      "Given --> VBN --> VERBO",
      "that --> IN --> CONJUNÇÃO",
      "a --> DT --> ARTIGO",
      "student --> NN --> SUBSTANTIVO",
      "wants --> VBZ --> VERBO",
      "to --> TO --> PREPOSIÇÃO",
      "check --> VB --> VERBO",
      "his --> PRP$ --> PRONOME",
      "grades --> NNS --> SUBSTANTIVO",
      "and --> CC --> CONJUNÇÃO",
      "he --> PRP --> PRONOME",
      "is --> VBZ --> VERBO",
      "logged --> VBN --> VERBO",
      ", --> , --> INVÁLIDO",
      "when --> WRB --> ADVÉRBIO",
      "he --> PRP --> PRONOME",
      "clicks --> VBZ --> VERBO",
      "on --> IN --> CONJUNÇÃO",
      "his --> PRP$ --> PRONOME",
      "profile --> NN --> SUBSTANTIVO",
      "and --> CC --> CONJUNÇÃO",
      "clicks --> VBZ --> VERBO",
      "the --> DT --> ARTIGO",
      "Grades --> NNP --> SUBSTANTIVO",
      "button --> NN --> SUBSTANTIVO",
      ", --> , --> INVÁLIDO",
      "then --> RB --> ADVÉRBIO",
      "his --> PRP$ --> PRONOME",
      "grades --> NNS --> SUBSTANTIVO",
      "should --> MD --> VERBO",
      "be --> VB --> VERBO",
      "displayed --> VBN --> VERBO",
      ". --> . --> INVÁLIDO"
    ],
    "erros": null
  },
  {
    "texto": "Given the user wants to search for the restaurants closest to his location, when he clicks on the restaurants icon, then a map of his location should be displayed with the closest restaurants.",
    "tecnologia": "NLTK",
    "tempo": "0,63554 segundos",
    "bemFormado": true,
    "atomico": true,
    "minimo": true,
    "preCondicao": "Given the user want to search for the restaurants closest to his location ,",
    "acao": "when he click on the restaurants icon ,",
    "finalidade": "then a map of his location should be display with the closest restaurants .",
    "tags": [
      "Given --> VBN --> VERBO",
      "the --> DT --> ARTIGO",
      "user --> NN --> SUBSTANTIVO",
      "want --> VBP --> VERBO",
      "to --> TO --> PREPOSIÇÃO",
      "search --> VB --> VERBO",
      "for --> IN --> CONJUNÇÃO",
      "the --> DT --> ARTIGO",
      "restaurants --> NNS --> SUBSTANTIVO",
      "closest --> VBP --> VERBO",
      "to --> TO --> PREPOSIÇÃO",
      "his --> PRP$ --> PRONOME",
      "location --> NN --> SUBSTANTIVO",
      ", --> , --> INVÁLIDO",
      "when --> WRB --> ADVÉRBIO",
      "he --> PRP --> PRONOME",
      "click --> VBZ --> VERBO",
      "on --> IN --> CONJUNÇÃO",
      "the --> DT --> ARTIGO",
      "restaurants --> NNS --> SUBSTANTIVO",
      "icon --> NN --> SUBSTANTIVO",
      ", --> , --> INVÁLIDO",
      "then --> RB --> ADVÉRBIO",
      "a --> DT --> ARTIGO",
      "map --> NN --> SUBSTANTIVO",
      "of --> IN --> CONJUNÇÃO",
      "his --> PRP$ --> PRONOME",
      "location --> NN --> SUBSTANTIVO",
      "should --> MD --> VERBO",
      "be --> VB --> VERBO",
      "display --> VBN --> VERBO",
      "with --> IN --> CONJUNÇÃO",
      "the --> DT --> ARTIGO",
      "closest --> JJS --> ADJETIVO",
      "restaurants --> NNS --> SUBSTANTIVO",
      ". --> . --> INVÁLIDO"
    ],
    "erros": null
  },
  {
    "texto": "Given the user wants to search for the restaurants closest to his location, when he clicks on the restaurants icon, then a map of his location should be displayed with the closest restaurants.",
    "tecnologia": "spaCy",
    "tempo": "1,03974 segundos",
    "bemFormado": true,
    "atomico": true,
    "minimo": true,
    "preCondicao": "Given the user wants to search for the restaurants closest to his location ,",
    "acao": "when he clicks on the restaurants icon ,",
    "finalidade": "then a map of his location should be displayed with the closest restaurants .",
    "tags": [
      "Given --> VBN --> VERBO",
      "the --> DT --> ARTIGO",
      "user --> NN --> SUBSTANTIVO",
      "wants --> VBZ --> VERBO",
      "to --> TO --> PREPOSIÇÃO",
      "search --> VB --> VERBO",
      "for --> IN --> CONJUNÇÃO",
      "the --> DT --> ARTIGO",
      "restaurants --> NNS --> SUBSTANTIVO",
      "closest --> JJS --> ADJETIVO",
      "to --> IN --> CONJUNÇÃO",
      "his --> PRP$ --> PRONOME",
      "location --> NN --> SUBSTANTIVO",
      ", --> , --> INVÁLIDO",
      "when --> WRB --> ADVÉRBIO",
      "he --> PRP --> PRONOME",
      "clicks --> VBZ --> VERBO",
      "on --> IN --> CONJUNÇÃO",
      "the --> DT --> ARTIGO",
      "restaurants --> NNS --> SUBSTANTIVO",
      "icon --> NN --> SUBSTANTIVO",
      ", --> , --> INVÁLIDO",
      "then --> RB --> ADVÉRBIO",
      "a --> DT --> ARTIGO",
      "map --> NN --> SUBSTANTIVO",
      "of --> IN --> CONJUNÇÃO",
      "his --> PRP$ --> PRONOME",
      "location --> NN --> SUBSTANTIVO",
      "should --> MD --> VERBO",
      "be --> VB --> VERBO",
      "displayed --> VBN --> VERBO",
      "with --> IN --> CONJUNÇÃO",
      "the --> DT --> ARTIGO",
      "closest --> JJS --> ADJETIVO",
      "restaurants --> NNS --> SUBSTANTIVO",
      ". --> . --> INVÁLIDO"
    ],
    "erros": null
  },
  {
    "texto": "Given the lawyer wants to check the status of his cases and he is logged, when he clicks on the My Cases button then a list of his cases should be displayed in descending order from the newest to the oldest along with his status.",
    "tecnologia": "NLTK",
    "tempo": "0,63642 segundos",
    "bemFormado": true,
    "atomico": true,
    "minimo": true,
    "preCondicao": "Given the lawyer want to check the status of his case and he be log ,",
    "acao": "when he click on the My Cases button",
    "finalidade": "then a list of his case should be display in descend order from the newest to the oldest along with his status .",
    "tags": [
      "Given --> VBN --> VERBO",
      "the --> DT --> ARTIGO",
      "lawyer --> NN --> SUBSTANTIVO",
      "want --> VBP --> VERBO",
      "to --> TO --> PREPOSIÇÃO",
      "check --> VB --> VERBO",
      "the --> DT --> ARTIGO",
      "status --> NN --> SUBSTANTIVO",
      "of --> IN --> CONJUNÇÃO",
      "his --> PRP$ --> PRONOME",
      "case --> NN --> SUBSTANTIVO",
      "and --> CC --> CONJUNÇÃO",
      "he --> PRP --> PRONOME",
      "be --> VB --> VERBO",
      "log --> VBN --> VERBO",
      ", --> , --> INVÁLIDO",
      "when --> WRB --> ADVÉRBIO",
      "he --> PRP --> PRONOME",
      "click --> VBZ --> VERBO",
      "on --> IN --> CONJUNÇÃO",
      "the --> DT --> ARTIGO",
      "My --> NNP --> SUBSTANTIVO",
      "Cases --> NNP --> SUBSTANTIVO",
      "button --> NN --> SUBSTANTIVO",
      "then --> RB --> ADVÉRBIO",
      "a --> DT --> ARTIGO",
      "list --> NN --> SUBSTANTIVO",
      "of --> IN --> CONJUNÇÃO",
      "his --> PRP$ --> PRONOME",
      "case --> NN --> SUBSTANTIVO",
      "should --> MD --> VERBO",
      "be --> VB --> VERBO",
      "display --> VBN --> VERBO",
      "in --> IN --> CONJUNÇÃO",
      "descend --> JJ --> ADJETIVO",
      "order --> NN --> SUBSTANTIVO",
      "from --> IN --> CONJUNÇÃO",
      "the --> DT --> ARTIGO",
      "newest --> JJS --> ADJETIVO",
      "to --> TO --> PREPOSIÇÃO",
      "the --> DT --> ARTIGO",
      "oldest --> JJS --> ADJETIVO",
      "along --> IN --> CONJUNÇÃO",
      "with --> IN --> CONJUNÇÃO",
      "his --> PRP$ --> PRONOME",
      "status --> NN --> SUBSTANTIVO",
      ". --> . --> INVÁLIDO"
    ],
    "erros": null
  },
  {
    "texto": "Given the lawyer wants to check the status of his cases and he is logged, when he clicks on the My Cases button then a list of his cases should be displayed in descending order from the newest to the oldest along with his status.",
    "tecnologia": "spaCy",
    "tempo": "1,1818 segundos",
    "bemFormado": true,
    "atomico": true,
    "minimo": true,
    "preCondicao": "Given the lawyer wants to check the status of his cases and he is logged ,",
    "acao": "when he clicks on the My Cases button",
    "finalidade": "then a list of his cases should be displayed in descending order from the newest to the oldest along with his status .",
    "tags": [
      "Given --> VBN --> VERBO",
      "the --> DT --> ARTIGO",
      "lawyer --> NN --> SUBSTANTIVO",
      "wants --> VBZ --> VERBO",
      "to --> TO --> PREPOSIÇÃO",
      "check --> VB --> VERBO",
      "the --> DT --> ARTIGO",
      "status --> NN --> SUBSTANTIVO",
      "of --> IN --> CONJUNÇÃO",
      "his --> PRP$ --> PRONOME",
      "cases --> NNS --> SUBSTANTIVO",
      "and --> CC --> CONJUNÇÃO",
      "he --> PRP --> PRONOME",
      "is --> VBZ --> VERBO",
      "logged --> VBN --> VERBO",
      ", --> , --> INVÁLIDO",
      "when --> WRB --> ADVÉRBIO",
      "he --> PRP --> PRONOME",
      "clicks --> VBZ --> VERBO",
      "on --> IN --> CONJUNÇÃO",
      "the --> DT --> ARTIGO",
      "My --> PRP$ --> PRONOME",
      "Cases --> NNS --> SUBSTANTIVO",
      "button --> NN --> SUBSTANTIVO",
      "then --> RB --> ADVÉRBIO",
      "a --> DT --> ARTIGO",
      "list --> NN --> SUBSTANTIVO",
      "of --> IN --> CONJUNÇÃO",
      "his --> PRP$ --> PRONOME",
      "cases --> NNS --> SUBSTANTIVO",
      "should --> MD --> VERBO",
      "be --> VB --> VERBO",
      "displayed --> VBN --> VERBO",
      "in --> IN --> CONJUNÇÃO",
      "descending --> VBG --> VERBO",
      "order --> NN --> SUBSTANTIVO",
      "from --> IN --> CONJUNÇÃO",
      "the --> DT --> ARTIGO",
      "newest --> JJS --> ADJETIVO",
      "to --> IN --> CONJUNÇÃO",
      "the --> DT --> ARTIGO",
      "oldest --> JJS --> ADJETIVO",
      "along --> IN --> CONJUNÇÃO",
      "with --> IN --> CONJUNÇÃO",
      "his --> PRP$ --> PRONOME",
      "status --> NN --> SUBSTANTIVO",
      ". --> . --> INVÁLIDO"
    ],
    "erros": null
  }
]